README.rst
setup.cfg
setup.py
packman/__init__.py
packman/apt.py
packman/codes.py
packman/definitions.py
packman/dictconfig.py
packman/fpm.py
packman/logger.py
packman/packman.py
packman/pkm.py
packman/python.py
packman/retrieve.py
packman/ruby.py
packman/six.py
packman/templater.py
packman/utils.py
packman/yum.py
packman.egg-info/PKG-INFO
packman.egg-info/SOURCES.txt
packman.egg-info/dependency_links.txt
packman.egg-info/entry_points.txt
packman.egg-info/requires.txt
packman.egg-info/top_level.txt