Metadata-Version: 1.1
Name: packman
Version: 0.5.0
Summary: Package Generator
Home-page: https://github.com/cloudify-cosmo/packman
Author: nir0s
Author-email: nir36g@gmail.com
License: LICENSE
Platform: UNKNOWN
Classifier: Programming Language :: Python
Classifier: Natural Language :: English
Classifier: Environment :: Console
Classifier: Intended Audience :: Developers
Classifier: Intended Audience :: Information Technology
Classifier: License :: OSI Approved :: Apache Software License
Classifier: Operating System :: POSIX :: Linux
Classifier: Topic :: Software Development :: Libraries :: Python Modules
Classifier: Topic :: System :: Archiving :: Packaging
